trade.py
tradegui.py
tradedangerous/__init__.py
tradedangerous/cache.py
tradedangerous/cli.py
tradedangerous/corrections.py
tradedangerous/csvexport.py
tradedangerous/edscupdate.py
tradedangerous/edsmupdate.py
tradedangerous/formatting.py
tradedangerous/fs.py
tradedangerous/gui.py
tradedangerous/mapping.py
tradedangerous/prices.py
tradedangerous/submit-distances.py
tradedangerous/tools.py
tradedangerous/tradecalc.py
tradedangerous/tradedb.py
tradedangerous/tradeenv.py
tradedangerous/tradeenv.pyi
tradedangerous/tradeexcept.py
tradedangerous/tradegame.py
tradedangerous/tradeorm.py
tradedangerous/transfers.py
tradedangerous/utils.py
tradedangerous/version.py
tradedangerous/archive/jsonprices.py
tradedangerous/archive/commands/update_gui.py
tradedangerous/archive/docs/sphinx/conf.py
tradedangerous/archive/plugins/edapi_plug.py
tradedangerous/archive/plugins/journal_plug.py
tradedangerous/archive/plugins/netlog_plug.py
tradedangerous/commands/TEMPLATE.py
tradedangerous/commands/__init__.py
tradedangerous/commands/buildcache_cmd.py
tradedangerous/commands/buy_cmd.py
tradedangerous/commands/commandenv.py
tradedangerous/commands/exceptions.py
tradedangerous/commands/export_cmd.py
tradedangerous/commands/import_cmd.py
tradedangerous/commands/local_cmd.py
tradedangerous/commands/market_cmd.py
tradedangerous/commands/nav_cmd.py
tradedangerous/commands/olddata_cmd.py
tradedangerous/commands/parsing.py
tradedangerous/commands/rares_cmd.py
tradedangerous/commands/run_cmd.py
tradedangerous/commands/sell_cmd.py
tradedangerous/commands/shipvendor_cmd.py
tradedangerous/commands/station_cmd.py
tradedangerous/commands/trade_cmd.py
tradedangerous/commands/update_cmd.py
tradedangerous/db/__init__.py
tradedangerous/db/adapter.py
tradedangerous/db/config.py
tradedangerous/db/engine.py
tradedangerous/db/lifecycle.py
tradedangerous/db/locks.py
tradedangerous/db/orm_models.py
tradedangerous/db/paths.py
tradedangerous/db/test_utils.py
tradedangerous/db/utils.py
tradedangerous/mfd/__init__.py
tradedangerous-12.11.6.dist-info/licenses/LICENSE
tradedangerous-12.11.6.dist-info/METADATA
tradedangerous-12.11.6.dist-info/WHEEL
tradedangerous-12.11.6.dist-info/entry_points.txt
tradedangerous-12.11.6.dist-info/top_level.txt
tradedangerous-12.11.6.dist-info/RECORD
