Metadata-Version: 2.4
Name: tradedangerous
Version: 12.11.6
Summary: Trade-Dangerous is a set of powerful trading tools for Elite Dangerous, organized around one of the most powerful trade run optimizers available.
Home-page: https://github.com/eyeonus/Trade-Dangerous
Author: Stefan 'Tromador' Morrell, Bernd Gollesch
Author-email: eyeonus <eyeonus@gmail.com>, Oliver 'kfsone' Smith <oliver@kfs.org>
License-Expression: MPL-2.0
Project-URL: Homepage, https://github.com/eyeonus/Trade-Dangerous
Project-URL: Bug Tracker, https://github.com/eyeonus/Trade-Dangerous/issues
Project-URL: Documentation, https://github.com/eyeonus/Trade-Dangerous/wiki
Project-URL: Source Code, https://github.com/eyeonus/Trade-Dangerous
Keywords: trade,elite,elite-dangerous
Classifier: Programming Language :: Python :: 3
Classifier: Programming Language :: Python :: 3.10
Classifier: Programming Language :: Python :: 3.11
Classifier: Programming Language :: Python :: 3.12
Classifier: Programming Language :: Python :: 3.13
Classifier: Operating System :: OS Independent
Requires-Python: >=3.10
License-File: LICENSE
Requires-Dist: appJar
Requires-Dist: ijson>=3.1
Requires-Dist: importlib-metadata>=1
Requires-Dist: orjson>=3.11.5
Requires-Dist: requests
Requires-Dist: rich==13.7.1
Requires-Dist: sqlalchemy<3.0,>=2.0
Provides-Extra: build
Requires-Dist: uv~=0.9.21; extra == "build"
Provides-Extra: dev-extras
Requires-Dist: ipython; extra == "dev-extras"
Provides-Extra: notebooks
Requires-Dist: jupyter>=1.1.1; extra == "notebooks"
Dynamic: home-page
Dynamic: license-file
Dynamic: requires-python
